aletheia_probe/__init__.py
aletheia_probe/article_retraction_checker.py
aletheia_probe/backend_exceptions.py
aletheia_probe/batch_assessor.py
aletheia_probe/bibtex_parser.py
aletheia_probe/cli.py
aletheia_probe/confidence_utils.py
aletheia_probe/config.py
aletheia_probe/constants.py
aletheia_probe/data_models.py
aletheia_probe/dispatcher.py
aletheia_probe/enums.py
aletheia_probe/fallback_chain.py
aletheia_probe/fallback_executor.py
aletheia_probe/logging_config.py
aletheia_probe/models.py
aletheia_probe/normalizer.py
aletheia_probe/openalex.py
aletheia_probe/output_formatter.py
aletheia_probe/py.typed
aletheia_probe/quality_assessment.py
aletheia_probe/retry_utils.py
aletheia_probe/risk_calculator.py
aletheia_probe/validation.py
aletheia_probe/backends/__init__.py
aletheia_probe/backends/algerian_ministry.py
aletheia_probe/backends/base.py
aletheia_probe/backends/bealls.py
aletheia_probe/backends/crossref_analyzer.py
aletheia_probe/backends/custom_list.py
aletheia_probe/backends/doaj.py
aletheia_probe/backends/fallback_mixin.py
aletheia_probe/backends/kscien_hijacked_journals.py
aletheia_probe/backends/kscien_predatory_conferences.py
aletheia_probe/backends/kscien_publishers.py
aletheia_probe/backends/kscien_standalone_journals.py
aletheia_probe/backends/openalex_analyzer.py
aletheia_probe/backends/predatoryjournals.py
aletheia_probe/backends/protocols.py
aletheia_probe/backends/retraction_watch.py
aletheia_probe/backends/scopus.py
aletheia_probe/cache/__init__.py
aletheia_probe/cache/acronym_cache.py
aletheia_probe/cache/assessment_cache.py
aletheia_probe/cache/base.py
aletheia_probe/cache/connection_utils.py
aletheia_probe/cache/custom_list_manager.py
aletheia_probe/cache/data_source_manager.py
aletheia_probe/cache/journal_cache.py
aletheia_probe/cache/openalex_cache.py
aletheia_probe/cache/retraction_cache.py
aletheia_probe/cache/schema.py
aletheia_probe/cache_sync/__init__.py
aletheia_probe/cache_sync/cache_cleanup_registry.py
aletheia_probe-0.8.0.dist-info/licenses/LICENSE
aletheia_probe-0.8.0.dist-info/METADATA
aletheia_probe-0.8.0.dist-info/WHEEL
aletheia_probe-0.8.0.dist-info/entry_points.txt
aletheia_probe-0.8.0.dist-info/top_level.txt
aletheia_probe-0.8.0.dist-info/RECORD
