Metadata-Version: 2.4
Name: aletheia-probe
Version: 0.8.0
Summary: Automated tool for assessing predatory journals using multiple backend sources
Author: Aletheia Probe Project
Maintainer: Andreas.Florath@telekom.de
License: MIT License
Project-URL: Homepage, https://github.com/sustainet-guardian/aletheia-probe
Project-URL: Repository, https://github.com/sustainet-guardian/aletheia-probe.git
Project-URL: Issues, https://github.com/sustainet-guardian/aletheia-probe/issues
Project-URL: Documentation, https://github.com/sustainet-guardian/aletheia-probe#readme
Project-URL: Changelog, https://github.com/sustainet-guardian/aletheia-probe/blob/main/docs/CHANGELOG.md
Keywords: journal,predatory,assessment,research,academia,retraction,doaj,openalex,scholarly
Classifier: Development Status :: 4 - Beta
Classifier: Intended Audience :: Science/Research
Classifier: Intended Audience :: Education
Classifier: Topic :: Scientific/Engineering :: Information Analysis
Classifier: Topic :: Education
Classifier: Topic :: Internet :: WWW/HTTP :: Indexing/Search
Classifier: License :: OSI Approved :: MIT License
Classifier: Programming Language :: Python :: 3
Classifier: Programming Language :: Python :: 3.10
Classifier: Programming Language :: Python :: 3.11
Classifier: Programming Language :: Python :: 3.12
Classifier: Programming Language :: Python :: 3.13
Classifier: Operating System :: OS Independent
Classifier: Environment :: Console
Requires-Python: >=3.10
License-File: LICENSE
Requires-Dist: pydantic>=2.0.0
Requires-Dist: aiohttp>=3.8.0
Requires-Dist: aiofiles>=23.0.0
Requires-Dist: click>=8.0.0
Requires-Dist: pyyaml>=6.0
Requires-Dist: rarfile>=4.1
Requires-Dist: pypdf>=3.0.0
Requires-Dist: pybtex>=0.24.0
Requires-Dist: openpyxl>=3.0.0
Provides-Extra: dev
Requires-Dist: pytest>=7.0.0; extra == "dev"
Requires-Dist: pytest-asyncio>=0.21.0; extra == "dev"
Requires-Dist: pytest-cov>=4.0.0; extra == "dev"
Requires-Dist: pytest-benchmark>=4.0.0; extra == "dev"
Requires-Dist: pytest-xdist>=3.0.0; extra == "dev"
Requires-Dist: psutil>=5.9.0; extra == "dev"
Requires-Dist: black>=23.0.0; extra == "dev"
Requires-Dist: mypy>=1.0.0; extra == "dev"
Requires-Dist: ruff>=0.1.0; extra == "dev"
Requires-Dist: pre-commit>=3.0.0; extra == "dev"
Requires-Dist: types-PyYAML>=6.0.0; extra == "dev"
Requires-Dist: types-aiofiles>=23.0.0; extra == "dev"
Requires-Dist: types-openpyxl>=3.0.0; extra == "dev"
Requires-Dist: bandit>=1.7.0; extra == "dev"
Requires-Dist: safety>=3.0.0; extra == "dev"
Provides-Extra: release
Requires-Dist: build>=1.0.0; extra == "release"
Requires-Dist: twine>=4.0.0; extra == "release"
Requires-Dist: packaging>=23.0; extra == "release"
Requires-Dist: requests>=2.28.0; extra == "release"
Dynamic: license-file
